LICENSE
MANIFEST.in
README.md
setup.py
golosdata/__init__.py
golosdata/golosdata.py
golosdata/helpers.py
golosdata/utils.py
golosdata.egg-info/PKG-INFO
golosdata.egg-info/SOURCES.txt
golosdata.egg-info/dependency_links.txt
golosdata.egg-info/requires.txt
golosdata.egg-info/top_level.txt