Metadata-Version: 1.1
Name: golosdata
Version: 0.0.3
Summary: Python Utilities for parsing GOLOS blockchain
Home-page: https://github.com/Chainers/golosdata.git
Author: @steepshot
Author-email: steepshot.org@gmail.com
License: The MIT License (MIT)
